config.py
kakao.py
naver.py
sk.py
web.py
mseep_kimcp-1.0.1.dist-info/licenses/LICENSE
mseep_kimcp-1.0.1.dist-info/METADATA
mseep_kimcp-1.0.1.dist-info/WHEEL
mseep_kimcp-1.0.1.dist-info/top_level.txt
mseep_kimcp-1.0.1.dist-info/RECORD
